signal_cartographer/__init__.py
signal_cartographer/aethertap.py
signal_cartographer/aethertap_textual.py
signal_cartographer/command_parser.py
signal_cartographer/command_parser_enhanced.py
signal_cartographer/enhanced_ux.py
signal_cartographer/game_core.py
signal_cartographer/game_core_textual.py
signal_cartographer/main.py
signal_cartographer/performance_integration.py
signal_cartographer/performance_optimizations.py
signal_cartographer/progression_system.py
signal_cartographer/signal_art.py
signal_cartographer/signal_system.py
signal_cartographer/startup_enhanced.py
signal_cartographer/content/__init__.py
signal_cartographer/puzzles/__init__.py
signal_cartographer/puzzles/difficulty.py
signal_cartographer/puzzles/puzzle_base.py
signal_cartographer/puzzles/puzzle_manager.py
signal_cartographer/puzzles/audio_patterns/__init__.py
signal_cartographer/puzzles/audio_patterns/audio_conversion_puzzle.py
signal_cartographer/puzzles/audio_patterns/audio_library.py
signal_cartographer/puzzles/audio_patterns/audio_tools.py
signal_cartographer/puzzles/audio_patterns/harmonic_pattern_puzzle.py
signal_cartographer/puzzles/audio_patterns/morse_code_puzzle.py
signal_cartographer/puzzles/audio_patterns/pulse_sequence_puzzle.py
signal_cartographer/puzzles/audio_patterns/rhythm_pattern_puzzle.py
signal_cartographer/puzzles/audio_patterns/temporal_sequence_puzzle.py
signal_cartographer/puzzles/cryptographic/__init__.py
signal_cartographer/puzzles/cryptographic/caesar_cipher_puzzle.py
signal_cartographer/puzzles/cryptographic/cipher_library.py
signal_cartographer/puzzles/cryptographic/cipher_tools.py
signal_cartographer/puzzles/cryptographic/frequency_analysis_puzzle.py
signal_cartographer/puzzles/cryptographic/substitution_cipher_puzzle.py
signal_cartographer/puzzles/cryptographic/vigenere_cipher_puzzle.py
signal_cartographer/puzzles/logic_puzzles/__init__.py
signal_cartographer/puzzles/logic_puzzles/circuit_completion_puzzle.py
signal_cartographer-1.0.1.dist-info/licenses/LICENSE
signal_cartographer-1.0.1.dist-info/METADATA
signal_cartographer-1.0.1.dist-info/WHEEL
signal_cartographer-1.0.1.dist-info/entry_points.txt
signal_cartographer-1.0.1.dist-info/top_level.txt
signal_cartographer-1.0.1.dist-info/RECORD
