Metadata-Version: 2.4
Name: signal-cartographer
Version: 1.0.1
Summary: A sci-fi terminal-based signal analysis game with beautiful TUI interface
Author: Maverick
License-Expression: MIT
Project-URL: Homepage, https://github.com/maverickkamal/signal-cartographer
Project-URL: Repository, https://github.com/maverickkamal/signal-cartographer.git
Project-URL: Documentation, https://github.com/maverickkamal/signal-cartographer#readme
Project-URL: Bug Tracker, https://github.com/maverickkamal/signal-cartographer/issues
Keywords: game,sci-fi,terminal,tui,textual,signal-analysis
Classifier: Development Status :: 5 - Production/Stable
Classifier: Environment :: Console
Classifier: Intended Audience :: End Users/Desktop
Classifier: Operating System :: OS Independent
Classifier: Programming Language :: Python :: 3
Classifier: Programming Language :: Python :: 3.8
Classifier: Programming Language :: Python :: 3.9
Classifier: Programming Language :: Python :: 3.10
Classifier: Programming Language :: Python :: 3.11
Classifier: Programming Language :: Python :: 3.12
Classifier: Topic :: Games/Entertainment
Classifier: Topic :: Terminals
Classifier: Topic :: Software Development :: User Interfaces
Requires-Python: >=3.8
License-File: LICENSE
Requires-Dist: textual>=0.20.0
Requires-Dist: rich>=13.0.0
Requires-Dist: click>=8.0.0
Provides-Extra: dev
Requires-Dist: pytest>=7.0.0; extra == "dev"
Requires-Dist: black>=22.0.0; extra == "dev"
Requires-Dist: flake8>=5.0.0; extra == "dev"
Dynamic: license-file
